gxscalc/__init__.py
gxscalc/gxscalc.py
gxscalc-0.1.0.dist-info/LICENSE
gxscalc-0.1.0.dist-info/METADATA
gxscalc-0.1.0.dist-info/WHEEL
gxscalc-0.1.0.dist-info/top_level.txt
gxscalc-0.1.0.dist-info/RECORD
