Metadata-Version: 2.1
Name: gxscalc
Version: 0.1.0
Summary: A Python package for speed-based calculation of F-ZERO GX.
Home-page: https://github.com/cycloawaodorin/gxscalc
Author: KAZOON
Author-email: cycloawaodorin+pypi@gmail.com
Maintainer: KAZOON
Maintainer-email: cycloawaodorin+pypi@gmail.com
Classifier: Programming Language :: Python :: 3
Classifier: License :: OSI Approved :: MIT License
Classifier: Operating System :: OS Independent
Requires-Python: >=3.7
License-File: LICENSE
Requires-Dist: pandas
Requires-Dist: matplotlib
